license_authorize_win/__init__.py
license_authorize_win/_core.pyd
license_authorize_win/decode.pyd
license_authorize_win-1.0.10.dist-info/METADATA
license_authorize_win-1.0.10.dist-info/WHEEL
license_authorize_win-1.0.10.dist-info/top_level.txt
license_authorize_win-1.0.10.dist-info/RECORD
