Metadata-Version: 2.1
Name: license-authorize-win
Version: 1.0.10
Summary: A tools for license authorize in windows
Home-page: https://github.com/gisfanmachel/licenseAuthorize
Author: gisfanmachel
Author-email: gisfanmachel@gmail.com
License: UNKNOWN
Keywords: license,authorize,setuptools,development
Platform: UNKNOWN
Classifier: Development Status :: 3 - Alpha
Classifier: Intended Audience :: Developers
Classifier: Topic :: Software Development :: Build Tools
Classifier: License :: OSI Approved :: MIT License
Classifier: Programming Language :: Python :: 3
Classifier: Programming Language :: Python :: 3.7
Classifier: Programming Language :: Python :: 3.8
Classifier: Programming Language :: Python :: 3.9
Classifier: Programming Language :: Python :: 3.10
Classifier: Programming Language :: Python :: 3 :: Only
Requires-Python: >=3.7, <4
Requires-Dist: pycryptodome
